COPYING
README
ez_setup.py
setup.py
dbstore/__init__.py
dbstore/mysqlstore.py
dbstore/psycopgstore.py
dbstore/storage.py
dbstore.egg-info/PKG-INFO
dbstore.egg-info/SOURCES.txt
dbstore.egg-info/dependency_links.txt
dbstore.egg-info/top_level.txt
