Metadata-Version: 1.0
Name: dbstore
Version: 0.3
Summary: Database storage for flup session middleware.
Home-page: http://lukearno.com/projects/dbstore/
Author: Luke Arno
Author-email: luke.arno@gmail.com
License: LGPL2
Keywords: wsgi database mysql sessions flup
Platform: UNKNOWN
Classifier: Development Status :: 3 - Alpha
Classifier: Environment :: Web Environment
Classifier: Intended Audience :: Developers
Classifier: License :: OSI Approved :: GNU General Public License (GPL)
Classifier: Natural Language :: English
Classifier: Operating System :: OS Independent
Classifier: Programming Language :: Python
Classifier: Topic :: Software Development :: Libraries
Classifier: Topic :: Utilities
